{
  "son_guncelleme": "30.06.2026 17:29",
  "bist100_durum": "DÜŞÜŞ 📉 (%-0.43)",
  "toplam_hisse": 30,
  "hisseler": [
    {
      "hisse": "AHGAZ",
      "fiyat": 40.0,
      "skor": 95,
      "robot_karari": "GÜÇLÜ AL 🔥",
      "rsi_durumu": "Aşırı Alım 🔴 (RSI: 87.7)",
      "ideal_alim": 39.4,
      "tp": 43.07,
      "sl": 37.7,
      "s1": 36.6,
      "r1": 37.5,
      "direnc20": 37.62,
      "ma10": 36.48,
      "ma30": 33.59,
      "rsi_deger": 87.7,
      "hacim_orani": 2.1
    },
    {
      "hisse": "ALARK",
      "fiyat": 107.7,
      "skor": 80,
      "robot_karari": "GÜÇLÜ AL 🔥",
      "rsi_durumu": "Nötr ⚪ (RSI: 53.3)",
      "ideal_alim": 106.08,
      "tp": 116.36,
      "sl": 101.21,
      "s1": 105.2,
      "r1": 109.2,
      "direnc20": 111.7,
      "ma10": 103.33,
      "ma30": 101.01,
      "rsi_deger": 53.3,
      "hacim_orani": 0.8
    },
    {
      "hisse": "CATES",
      "fiyat": 40.68,
      "skor": 80,
      "robot_karari": "GÜÇLÜ AL 🔥",
      "rsi_durumu": "Nötr ⚪ (RSI: 58.8)",
      "ideal_alim": 40.07,
      "tp": 43.93,
      "sl": 38.24,
      "s1": 39.55,
      "r1": 41.21,
      "direnc20": 42.68,
      "ma10": 40.53,
      "ma30": 39.86,
      "rsi_deger": 58.8,
      "hacim_orani": 0.9
    },
    {
      "hisse": "CCOLA",
      "fiyat": 83.05,
      "skor": 80,
      "robot_karari": "GÜÇLÜ AL 🔥",
      "rsi_durumu": "Nötr ⚪ (RSI: 61.4)",
      "ideal_alim": 81.8,
      "tp": 88.0,
      "sl": 79.34,
      "s1": 82.05,
      "r1": 83.8,
      "direnc20": 85.5,
      "ma10": 79.85,
      "ma30": 80.29,
      "rsi_deger": 61.4,
      "hacim_orani": 0.6
    },
    {
      "hisse": "AKCNS",
      "fiyat": 227.7,
      "skor": 75,
      "robot_karari": "KADEMELİ AL 📈",
      "rsi_durumu": "Nötr ⚪ (RSI: 57.1)",
      "ideal_alim": 224.28,
      "tp": 250.14,
      "sl": 210.87,
      "s1": 207.0,
      "r1": 207.0,
      "direnc20": 230.0,
      "ma10": 204.5,
      "ma30": 211.33,
      "rsi_deger": 57.1,
      "hacim_orani": 2.2
    },
    {
      "hisse": "AEFES",
      "fiyat": 21.04,
      "skor": 70,
      "robot_karari": "KADEMELİ AL 📈",
      "rsi_durumu": "Nötr ⚪ (RSI: 62.9)",
      "ideal_alim": 20.72,
      "tp": 22.33,
      "sl": 20.07,
      "s1": 21.14,
      "r1": 21.56,
      "direnc20": 21.66,
      "ma10": 21.02,
      "ma30": 20.3,
      "rsi_deger": 62.9,
      "hacim_orani": 1.3
    },
    {
      "hisse": "AKSA",
      "fiyat": 12.1,
      "skor": 70,
      "robot_karari": "KADEMELİ AL 📈",
      "rsi_durumu": "Nötr ⚪ (RSI: 64.7)",
      "ideal_alim": 11.92,
      "tp": 13.11,
      "sl": 11.34,
      "s1": 11.6,
      "r1": 11.99,
      "direnc20": 12.79,
      "ma10": 11.91,
      "ma30": 11.2,
      "rsi_deger": 64.7,
      "hacim_orani": 1.1
    },
    {
      "hisse": "ARDYZ",
      "fiyat": 60.0,
      "skor": 70,
      "robot_karari": "KADEMELİ AL 📈",
      "rsi_durumu": "Nötr ⚪ (RSI: 53.0)",
      "ideal_alim": 59.1,
      "tp": 66.34,
      "sl": 55.24,
      "s1": 55.42,
      "r1": 57.67,
      "direnc20": 76.5,
      "ma10": 56.9,
      "ma30": 59.86,
      "rsi_deger": 53.0,
      "hacim_orani": 1.0
    },
    {
      "hisse": "BOBET",
      "fiyat": 18.99,
      "skor": 65,
      "robot_karari": "KADEMELİ AL 📈",
      "rsi_durumu": "Nötr ⚪ (RSI: 51.5)",
      "ideal_alim": 18.71,
      "tp": 20.23,
      "sl": 18.06,
      "s1": 18.82,
      "r1": 19.13,
      "direnc20": 21.0,
      "ma10": 19.14,
      "ma30": 18.88,
      "rsi_deger": 51.5,
      "hacim_orani": 0.4
    },
    {
      "hisse": "AGHOL",
      "fiyat": 34.58,
      "skor": 55,
      "robot_karari": "DİRENÇTE BEKLE 🛑",
      "rsi_durumu": "Aşırı Alım 🔴 (RSI: 65.7)",
      "ideal_alim": 34.06,
      "tp": 36.49,
      "sl": 33.15,
      "s1": 32.83,
      "r1": 33.77,
      "direnc20": 35.26,
      "ma10": 33.45,
      "ma30": 33.43,
      "rsi_deger": 65.7,
      "hacim_orani": 1.6
    },
    {
      "hisse": "BRSAN",
      "fiyat": 565.0,
      "skor": 55,
      "robot_karari": "DİRENÇTE BEKLE 🛑",
      "rsi_durumu": "Aşırı Satım 🟢 (RSI: 34.7)",
      "ideal_alim": 556.52,
      "tp": 612.71,
      "sl": 529.21,
      "s1": 552.0,
      "r1": 581.5,
      "direnc20": 648.5,
      "ma10": 584.8,
      "ma30": 563.48,
      "rsi_deger": 34.7,
      "hacim_orani": 0.7
    },
    {
      "hisse": "DEVA",
      "fiyat": 71.65,
      "skor": 55,
      "robot_karari": "DİRENÇTE BEKLE 🛑",
      "rsi_durumu": "Aşırı Alım 🔴 (RSI: 73.2)",
      "ideal_alim": 70.58,
      "tp": 75.49,
      "sl": 68.77,
      "s1": 69.57,
      "r1": 70.77,
      "direnc20": 73.4,
      "ma10": 70.78,
      "ma30": 67.13,
      "rsi_deger": 73.2,
      "hacim_orani": 0.6
    },
    {
      "hisse": "EGEEN",
      "fiyat": 5597.5,
      "skor": 50,
      "robot_karari": "DİRENÇTE BEKLE 🛑",
      "rsi_durumu": "Nötr ⚪ (RSI: 45.7)",
      "ideal_alim": 5513.54,
      "tp": 5901.07,
      "sl": 5369.82,
      "s1": 5495.0,
      "r1": 5632.5,
      "direnc20": 6000.0,
      "ma10": 5555.0,
      "ma30": 5633.08,
      "rsi_deger": 45.7,
      "hacim_orani": 0.9
    },
    {
      "hisse": "AKSEN",
      "fiyat": 81.25,
      "skor": 45,
      "robot_karari": "DİRENÇTE BEKLE 🛑",
      "rsi_durumu": "Nötr ⚪ (RSI: 59.2)",
      "ideal_alim": 80.03,
      "tp": 88.07,
      "sl": 76.13,
      "s1": 82.35,
      "r1": 84.4,
      "direnc20": 88.0,
      "ma10": 83.6,
      "ma30": 80.59,
      "rsi_deger": 59.2,
      "hacim_orani": 0.5
    },
    {
      "hisse": "ALFAS",
      "fiyat": 47.18,
      "skor": 45,
      "robot_karari": "DİRENÇTE BEKLE 🛑",
      "rsi_durumu": "Aşırı Satım 🟢 (RSI: 9.6)",
      "ideal_alim": 46.47,
      "tp": 54.04,
      "sl": 43.41,
      "s1": 46.06,
      "r1": 49.79,
      "direnc20": 66.6,
      "ma10": 51.53,
      "ma30": 54.74,
      "rsi_deger": 9.6,
      "hacim_orani": 0.5
    },
    {
      "hisse": "ALGYO",
      "fiyat": 4.02,
      "skor": 45,
      "robot_karari": "DİRENÇTE BEKLE 🛑",
      "rsi_durumu": "Aşırı Satım 🟢 (RSI: 7.0)",
      "ideal_alim": 3.96,
      "tp": 4.62,
      "sl": 3.7,
      "s1": 3.89,
      "r1": 4.02,
      "direnc20": 7.86,
      "ma10": 4.21,
      "ma30": 5.94,
      "rsi_deger": 7.0,
      "hacim_orani": 0.7
    },
    {
      "hisse": "BERA",
      "fiyat": 15.94,
      "skor": 45,
      "robot_karari": "DİRENÇTE BEKLE 🛑",
      "rsi_durumu": "Aşırı Satım 🟢 (RSI: 30.6)",
      "ideal_alim": 15.7,
      "tp": 17.27,
      "sl": 14.94,
      "s1": 15.98,
      "r1": 16.28,
      "direnc20": 18.54,
      "ma10": 16.77,
      "ma30": 16.94,
      "rsi_deger": 30.6,
      "hacim_orani": 0.4
    },
    {
      "hisse": "BRYAT",
      "fiyat": 1872.0,
      "skor": 45,
      "robot_karari": "DİRENÇTE BEKLE 🛑",
      "rsi_durumu": "Aşırı Satım 🟢 (RSI: 33.0)",
      "ideal_alim": 1843.92,
      "tp": 1966.0,
      "sl": 1801.5,
      "s1": 1852.67,
      "r1": 1938.67,
      "direnc20": 2110.0,
      "ma10": 1924.7,
      "ma30": 1959.3,
      "rsi_deger": 33.0,
      "hacim_orani": 0.5
    },
    {
      "hisse": "BUCIM",
      "fiyat": 5.68,
      "skor": 45,
      "robot_karari": "DİRENÇTE BEKLE 🛑",
      "rsi_durumu": "Aşırı Satım 🟢 (RSI: 34.2)",
      "ideal_alim": 5.59,
      "tp": 5.96,
      "sl": 5.51,
      "s1": 5.68,
      "r1": 5.79,
      "direnc20": 6.43,
      "ma10": 5.86,
      "ma30": 5.97,
      "rsi_deger": 34.2,
      "hacim_orani": 0.3
    },
    {
      "hisse": "CANTE",
      "fiyat": 1.37,
      "skor": 45,
      "robot_karari": "DİRENÇTE BEKLE 🛑",
      "rsi_durumu": "Aşırı Satım 🟢 (RSI: 32.0)",
      "ideal_alim": 1.35,
      "tp": 1.46,
      "sl": 1.3,
      "s1": 1.36,
      "r1": 1.4,
      "direnc20": 1.61,
      "ma10": 1.43,
      "ma30": 1.49,
      "rsi_deger": 32.0,
      "hacim_orani": 0.7
    },
    {
      "hisse": "DOAS",
      "fiyat": 179.3,
      "skor": 45,
      "robot_karari": "DİRENÇTE BEKLE 🛑",
      "rsi_durumu": "Aşırı Satım 🟢 (RSI: 24.0)",
      "ideal_alim": 176.61,
      "tp": 190.87,
      "sl": 170.62,
      "s1": 182.0,
      "r1": 184.5,
      "direnc20": 209.1,
      "ma10": 189.39,
      "ma30": 189.12,
      "rsi_deger": 24.0,
      "hacim_orani": 0.9
    },
    {
      "hisse": "ECILC",
      "fiyat": 74.9,
      "skor": 45,
      "robot_karari": "DİRENÇTE BEKLE 🛑",
      "rsi_durumu": "Aşırı Satım 🟢 (RSI: 34.5)",
      "ideal_alim": 73.78,
      "tp": 81.01,
      "sl": 70.32,
      "s1": 74.87,
      "r1": 76.27,
      "direnc20": 89.05,
      "ma10": 80.08,
      "ma30": 83.15,
      "rsi_deger": 34.5,
      "hacim_orani": 0.6
    },
    {
      "hisse": "ARENA",
      "fiyat": 27.42,
      "skor": 35,
      "robot_karari": "DİRENÇTE BEKLE 🛑",
      "rsi_durumu": "Nötr ⚪ (RSI: 54.7)",
      "ideal_alim": 27.01,
      "tp": 30.11,
      "sl": 25.4,
      "s1": 26.87,
      "r1": 27.67,
      "direnc20": 32.88,
      "ma10": 28.01,
      "ma30": 28.25,
      "rsi_deger": 54.7,
      "hacim_orani": 0.3
    },
    {
      "hisse": "AKFGY",
      "fiyat": 2.76,
      "skor": 25,
      "robot_karari": "DİRENÇTE BEKLE 🛑",
      "rsi_durumu": "Nötr ⚪ (RSI: 53.2)",
      "ideal_alim": 2.72,
      "tp": 2.92,
      "sl": 2.64,
      "s1": 2.72,
      "r1": 2.86,
      "direnc20": 2.9,
      "ma10": 2.81,
      "ma30": 2.79,
      "rsi_deger": 53.2,
      "hacim_orani": 0.9
    },
    {
      "hisse": "ALBRK",
      "fiyat": 8.1,
      "skor": 25,
      "robot_karari": "DİRENÇTE BEKLE 🛑",
      "rsi_durumu": "Nötr ⚪ (RSI: 54.4)",
      "ideal_alim": 7.98,
      "tp": 8.66,
      "sl": 7.68,
      "s1": 8.02,
      "r1": 8.3,
      "direnc20": 9.15,
      "ma10": 8.45,
      "ma30": 8.22,
      "rsi_deger": 54.4,
      "hacim_orani": 0.7
    },
    {
      "hisse": "ASTOR",
      "fiyat": 276.5,
      "skor": 25,
      "robot_karari": "DİRENÇTE BEKLE 🛑",
      "rsi_durumu": "Nötr ⚪ (RSI: 47.4)",
      "ideal_alim": 272.35,
      "tp": 313.0,
      "sl": 254.38,
      "s1": 273.17,
      "r1": 286.67,
      "direnc20": 385.75,
      "ma10": 292.73,
      "ma30": 308.36,
      "rsi_deger": 47.4,
      "hacim_orani": 0.6
    },
    {
      "hisse": "CIMSA",
      "fiyat": 47.1,
      "skor": 25,
      "robot_karari": "DİRENÇTE BEKLE 🛑",
      "rsi_durumu": "Nötr ⚪ (RSI: 40.2)",
      "ideal_alim": 46.39,
      "tp": 50.12,
      "sl": 44.84,
      "s1": 47.06,
      "r1": 49.18,
      "direnc20": 53.9,
      "ma10": 49.33,
      "ma30": 50.31,
      "rsi_deger": 40.2,
      "hacim_orani": 1.3
    },
    {
      "hisse": "CWENE",
      "fiyat": 38.0,
      "skor": 25,
      "robot_karari": "DİRENÇTE BEKLE 🛑",
      "rsi_durumu": "Nötr ⚪ (RSI: 55.0)",
      "ideal_alim": 37.43,
      "tp": 41.96,
      "sl": 35.03,
      "s1": 36.14,
      "r1": 37.16,
      "direnc20": 45.14,
      "ma10": 38.93,
      "ma30": 38.75,
      "rsi_deger": 55.0,
      "hacim_orani": 1.4
    },
    {
      "hisse": "ENJSA",
      "fiyat": 102.4,
      "skor": 25,
      "robot_karari": "DİRENÇTE BEKLE 🛑",
      "rsi_durumu": "Nötr ⚪ (RSI: 46.1)",
      "ideal_alim": 100.86,
      "tp": 109.04,
      "sl": 97.42,
      "s1": 103.43,
      "r1": 107.03,
      "direnc20": 114.0,
      "ma10": 105.74,
      "ma30": 108.12,
      "rsi_deger": 46.1,
      "hacim_orani": 0.9
    },
    {
      "hisse": "EUPWR",
      "fiyat": 83.85,
      "skor": 25,
      "robot_karari": "DİRENÇTE BEKLE 🛑",
      "rsi_durumu": "Nötr ⚪ (RSI: 39.4)",
      "ideal_alim": 82.59,
      "tp": 96.43,
      "sl": 77.14,
      "s1": 78.03,
      "r1": 83.33,
      "direnc20": 107.1,
      "ma10": 86.5,
      "ma30": 84.89,
      "rsi_deger": 39.4,
      "hacim_orani": 0.4
    }
  ],
  "sektor_ortalamalar": {
    "Enerji": 45.6,
    "Holding": 67.5,
    "Gida": 65.0,
    "Cimento": 47.5,
    "Kimya": 67.5,
    "Teknoloji": 52.5,
    "DemirCelik": 48.3,
    "Ilac": 55.0,
    "Tekstil": 50.0,
    "Gyo": 35.0,
    "Otomotiv": 45.0,
    "Banka": 25.0
  },
  "en_guclu_sektor": [
    "Holding",
    67.5
  ],
  "en_zayif_sektor": [
    "Banka",
    25.0
  ]
}